imc2zarr/__init__.py
imc2zarr/converter.py
imc2zarr/imclib/__init__.py
imc2zarr/imclib/imcdataparser.py
imc2zarr/imclib/imcraw.py
imc2zarr/imclib/mcdmeta.py
imc2zarr/imclib/mcdutils.py
imc2zarr/imclib/mcdxmlparser.py
imc2zarr/imclib/metadefs.py
imc2zarr-0.2.0.dist-info/LICENSE
imc2zarr-0.2.0.dist-info/METADATA
imc2zarr-0.2.0.dist-info/WHEEL
imc2zarr-0.2.0.dist-info/entry_points.txt
imc2zarr-0.2.0.dist-info/top_level.txt
imc2zarr-0.2.0.dist-info/RECORD
