Metadata-Version: 2.1
Name: imc2zarr
Version: 0.2.0
Summary: IMC scan to Zarr conversion
Home-page: https://gitlab.developers.cam.ac.uk/astronomy/camcead/imaxt/imc2zarr
Author: Mo Alsad and Eduardo Gonzalez Solares
Author-email: "msa51@cam.ac.uk
Project-URL: Bug Tracker, https://gitlab.developers.cam.ac.uk/astronomy/camcead/imaxt/imc2zarr/-/issues
Classifier: Programming Language :: Python :: 3
Classifier: License :: OSI Approved :: MIT License
Classifier: Operating System :: OS Independent
Requires-Python: >=3.7
License-File: LICENSE
Requires-Dist: click
Requires-Dist: numpy
Requires-Dist: pandas
Requires-Dist: python-dateutil
Requires-Dist: xarray
Requires-Dist: zarr
